<?xml version="1.0" encoding="utf-8"?>
<iasettings>
  <projectproperties>
    <manufacturer>User</manufacturer>
    <productname>ProxyPS3</productname>
    <productversion>1.0.0.0</productversion>
    <productcode>{6f5c120c-3d97-4456-9017-33683fc285bc}</productcode>
    <upgradecode>{c7d2f1f7-b859-4df5-b592-dbc6633d3fb3}</upgradecode>
    <language>0</language>
    <languagename>English</languagename>
  </projectproperties>
  <summary>
    <title>ProxyPS3</title>
    <subject>ProxyPS3</subject>
    <author>User</author>
    <summarycomments>ProxyPS3</summarycomments>
    <revisioncode>{3e309589-b9b0-4110-bbed-92a34043287d}</revisioncode>
    <uacelevation>highestAvailable</uacelevation>
  </summary>
  <addremove>
    <publishername>User</publishername>
    <contactname>User</contactname>
    <helplink>http://www.mywebsite.com</helplink>
    <productupdatelink>http://www.mywebsite.com</productupdatelink>
    <addremovecomments>All Rights Reserved</addremovecomments>
    <iconfile />
  </addremove>
  <codegen>
    <generateincludefiles>0</generateincludefiles>
    <generatefeatures>1</generatefeatures>
    <refreshscript>0</refreshscript>
  </codegen>
  <compilervariables>
    <variables />
  </compilervariables>
  <build>
    <buildtype>0</buildtype>
    <buildasmsi>False</buildasmsi>
    <cachesources>1</cachesources>
  </build>
  <targetfolders />
  <files>
    <filedetails filename="C:\Users\User\source\repos\ProxyPS3\WindowsApp3\bin\Release\ProxyPS3.exe" targetlocation="$TARGETDIR$" type="1" generatenativeimage="0" registerassembly="0" runinstallerclass="0" createshortcut="1" runprogram="0" installfilecommand="0" />
  </files>
  <dependencies />
  <registry />
  <dialogtheme>
    <themename>Official</themename>
  </dialogtheme>
  <authenticode>
    <sign>0</sign>
    <mode>0</mode>
    <certificatefile />
    <keyfile />
    <pfxfile />
    <productinfourl />
    <authpassword />
    <timestampurl />
    <signall>0</signall>
  </authenticode>
  <compression>
    <compressiontype>8</compressiontype>
    <encrypt>0</encrypt>
    <compressionpassword />
  </compression>
  <output>
    <outputtype>0</outputtype>
    <location />
    <filename />
    <calculatefilehash>0</calculatefilehash>
    <refreshrevisioncode>1</refreshrevisioncode>
  </output>
</iasettings>